col_gen_estimator/__init__.py
col_gen_estimator/_bdr_classifier.py
col_gen_estimator/_col_gen_classifier.py
col_gen_estimator/_dtree_classifier.py
col_gen_estimator/_version.py
col_gen_estimator/tests/__init__.py
col_gen_estimator/tests/test_bdrc.py
col_gen_estimator/tests/test_common.py
col_gen_estimator/tests/test_dtree.py
col_gen_estimator/tests/test_dtree_new.py
col_gen_estimator/tests/tic_tac_toe_dtree.py
examples/__init__.py
examples/dtree_experiment.py
ColGenEstimator-0.1.1.dist-info/LICENSE
ColGenEstimator-0.1.1.dist-info/METADATA
ColGenEstimator-0.1.1.dist-info/WHEEL
ColGenEstimator-0.1.1.dist-info/top_level.txt
ColGenEstimator-0.1.1.dist-info/RECORD
